cromwell_tools/__init__.py
cromwell_tools/cli.py
cromwell_tools/cromwell_api.py
cromwell_tools/cromwell_auth.py
cromwell_tools/exceptions.py
cromwell_tools/utilities.py
cromwell_tools/core/__init__.py
cromwell_tools/diag/__init__.py
cromwell_tools/diag/task_runtime.py
cromwell_tools/tests/__init__.py
cromwell_tools/tests/test.sh
cromwell_tools/tests/test_cli.py
cromwell_tools/tests/test_cromwell_api.py
cromwell_tools/tests/test_cromwell_auth.py
cromwell_tools/tests/test_utilities.py
cromwell_tools/tests/data/a.txt
cromwell_tools/tests/data/b.txt
cromwell_tools/tests/data/fake_account_key.json
cromwell_tools/tests/data/test_dependencies.json
cromwell_tools/tests/data/test_deps.zip
cromwell_tools/tests/data/test_inputs1.json
cromwell_tools/tests/data/test_inputs2.json
cromwell_tools/tests/data/test_labels.json
cromwell_tools/tests/data/test_options.json
cromwell_tools/tests/data/test_task.wdl
cromwell_tools/tests/data/test_workflow.wdl
cromwell_tools-2.4.1.dist-info/LICENSE
cromwell_tools-2.4.1.dist-info/METADATA
cromwell_tools-2.4.1.dist-info/WHEEL
cromwell_tools-2.4.1.dist-info/entry_points.txt
cromwell_tools-2.4.1.dist-info/top_level.txt
cromwell_tools-2.4.1.dist-info/RECORD
