Metadata-Version: 2.1
Name: cromwell-tools
Version: 2.4.1
Summary: Utilities for interacting with the Cromwell workflow engine
Home-page: http://github.com/broadinstitute/cromwell-tools
Author: Mint Team
Author-email: mintteam@broadinstitute.org
License: BSD 3-clause "New" or "Revised" License
Platform: UNKNOWN
Classifier: Development Status :: 4 - Beta
Classifier: Natural Language :: English
Classifier: License :: OSI Approved :: BSD License
Classifier: Operating System :: OS Independent
Classifier: Programming Language :: Python
Classifier: Programming Language :: Python :: 3.6
Classifier: Topic :: Scientific/Engineering :: Bio-Informatics
Requires-Dist: requests (<3,>=2.20.0)
Requires-Dist: six (>=1.11.0)
Requires-Dist: google-auth (<2,>=1.6.1)
Requires-Dist: setuptools-scm (<4,>=3.1.0)
Requires-Dist: google-api-python-client (<2,>=1.7)
Requires-Dist: python-dateutil (<3,>=2.8)
Provides-Extra: test
Requires-Dist: black (==19.3b0) ; extra == 'test'
Requires-Dist: flake8 (==3.7.7) ; extra == 'test'
Requires-Dist: mock (>=2.0.0) ; extra == 'test'
Requires-Dist: requests-mock (>=1.4.0) ; extra == 'test'
Requires-Dist: pre-commit (==1.14.4) ; extra == 'test'
Requires-Dist: pytest-cov (>=2.5.1) ; extra == 'test'
Requires-Dist: pytest (>=3.6.3) ; extra == 'test'
Requires-Dist: pytest-timeout (>=1.3.1) ; extra == 'test'
